[
    {
        "id": "423d1207-eeba-4858-8348-35ab13889fd7",
        "word": "adventurous",
        "phonetic": "ɐdvɛntʃɚɹəs ",
        "type": "adjective",
        "defineEn": "(of a person) eager to try new ideas, exciting things, and take risks",
        "defineVi": "(của một người) háo hức thử những ý tưởng mới, những điều thú vị và chấp nhận rủi ro"
    },
    {
        "id": "02796882-7ce4-4b29-8b40-3ecf67385e98",
        "word": "to alarm",
        "phonetic": "tʊ ɐlɑːɹm ",
        "type": "verb",
        "defineEn": "to scare someone or make them anxious",
        "defineVi": "để sợ ai đó hoặc làm cho họ lo lắng"
    },
    {
        "id": "e9318f27-2662-4bf9-a109-d948a1dd7fbe",
        "word": "alarmed",
        "phonetic": "ɐlɑːɹmd ",
        "type": "adjective",
        "defineEn": "worrying about or fearing something",
        "defineVi": "lo lắng về hoặc sợ hãi một cái gì đó",
        "hasImg": true
    },
    {
        "id": "ef6da1f1-49c0-43b0-8b28-cdf16727e576",
        "word": "daring",
        "phonetic": "dɛɹɪŋ ",
        "type": "adjective",
        "defineEn": "brave enough to take risks and do dangerous things",
        "defineVi": "đủ dũng cảm để chấp nhận rủi ro và làm những việc nguy hiểm",
        "hasImg": true
    },
    {
        "id": "e886ea08-baeb-42e7-989e-4b7c73c039c5",
        "word": "at-risk",
        "phonetic": "ætɹɪsk ",
        "type": "adjective",
        "defineEn": "likely to be harmed or attacked",
        "defineVi": "có khả năng bị tổn hại hoặc bị tấn công"
    },
    {
        "id": "d76423a9-0cff-4431-8ca0-fd8d28f065d6",
        "word": "risk",
        "phonetic": "ɹɪsk ",
        "type": "noun",
        "defineEn": "the possibility of something dangerous or unpleasant happening in the future; a situation that causes danger or problem",
        "defineVi": "khả năng xảy ra điều gì đó nguy hiểm hoặc khó chịu trong tương lai; một tình huống gây ra nguy hiểm hoặc vấn đề",
        "hasImg": true
    },
    {
        "id": "92cfa4c5-0674-4267-8dcf-8b5388254fdb",
        "word": "critical",
        "phonetic": "kɹɪɾɪkəl ",
        "type": "adjective",
        "defineEn": "(of a problem or situation) very serious and possibly disastrous",
        "defineVi": "(của một vấn đề hoặc tình huống) rất nghiêm trọng và có thể là thảm họa"
    },
    {
        "id": "e327e50c-bebf-414b-9b1a-f3ac23064ac6",
        "word": "deadly",
        "phonetic": "dɛdli ",
        "type": "adjective",
        "defineEn": "causing death or capable of causing death",
        "defineVi": "gây ra cái chết hoặc có khả năng gây ra cái chết",
        "hasImg": true
    },
    {
        "id": "49bc50ce-94c4-4fe0-ad3d-e2287a53c430",
        "word": "desperate",
        "phonetic": "dɛspɚɹət ",
        "type": "adjective",
        "defineEn": "(of people) dangerous or violent because of having no hope",
        "defineVi": "(của người) nguy hiểm hoặc bạo lực vì không có hy vọng"
    },
    {
        "id": "33e5a7f9-22da-419e-b455-de5deeab1fe7",
        "word": "offensive",
        "phonetic": "əfɛnsɪv ",
        "type": "adjective",
        "defineEn": "describing something that is upsetting or disrespectful",
        "defineVi": "mô tả một cái gì đó là khó chịu hoặc thiếu tôn trọng"
    },
    {
        "id": "93c4deb2-3307-4ef8-b343-8ef4bb5bf2fd",
        "word": "harmless",
        "phonetic": "hɑːɹmləs ",
        "type": "adjective",
        "defineEn": "causing no harm or damage",
        "defineVi": "không gây hại hoặc thiệt hại"
    },
    {
        "id": "eccc80c5-2225-437a-b107-465dd6cf4080",
        "word": "high-risk",
        "phonetic": "haɪɹɪsk ",
        "type": "adjective",
        "defineEn": "describing something that could become highly dangerous or harmful",
        "defineVi": "mô tả một cái gì đó mà có thể trở nên rất nguy hiểm hoặc có hại"
    },
    {
        "id": "895e16a6-9f0b-4355-89f4-936daec124f5",
        "word": "low-risk",
        "phonetic": "loʊɹɪsk ",
        "type": "adjective",
        "defineEn": "characterized by involving a small amount of danger and having very low possibility of causing injury or death",
        "defineVi": "đặc trưng bởi liên quan đến một lượng nhỏ nguy hiểm và có khả năng gây thương tích hoặc tử vong rất thấp"
    },
    {
        "id": "b832a7e5-df41-4853-9ab4-668e16bac32b",
        "word": "secure",
        "phonetic": "sᵻkjʊɹ ",
        "type": "adjective",
        "defineEn": "describing something that is away from danger",
        "defineVi": "mô tả một cái gì đó tránh xa nguy hiểm",
        "hasImg": true
    },
    {
        "id": "a2af6f29-53b4-4780-8059-7996073e7407",
        "word": "harmful",
        "phonetic": "hɑːɹmfəl ",
        "type": "adjective",
        "defineEn": "causing damage or negative effects to someone or something",
        "defineVi": "gây thiệt hại hoặc tác động tiêu cực đến ai đó hoặc một cái gì đó",
        "hasImg": true
    },
    {
        "id": "cf939ce4-bca5-496c-bdb8-27716e11c1d9",
        "word": "insecure",
        "phonetic": "ɪnsᵻkjʊɹ ",
        "type": "adjective",
        "defineEn": "describing something that is not safe",
        "defineVi": "mô tả cái gì đó không an toàn"
    },
    {
        "id": "04fa17bb-b36a-4450-8031-ef85e146650c",
        "word": "sound",
        "phonetic": "saʊnd ",
        "type": "adjective",
        "defineEn": "being financially safe and secure",
        "defineVi": "được an toàn và bảo đảm về tài chính"
    },
    {
        "id": "5beac12e-d71c-4c37-b482-54860c5620ff",
        "word": "nasty",
        "phonetic": "næsti ",
        "type": "adjective",
        "defineEn": "extremely serious, dangerous, or difficult to deal with",
        "defineVi": "cực kỳ nghiêm trọng, nguy hiểm hoặc khó giải quyết"
    },
    {
        "id": "4a7fcad6-39a1-4878-aeea-01479ff1a0f3",
        "word": "risky",
        "phonetic": "ɹɪski ",
        "type": "adjective",
        "defineEn": "having the potential of loss, danger, harm, or failure",
        "defineVi": "có khả năng mất mát, nguy hiểm, tổn hại hoặc thất bại",
        "hasImg": true
    },
    {
        "id": "6e458c96-9cf9-4b0b-838e-89a070b98920",
        "word": "to encounter",
        "phonetic": "tʊ ɛŋkaʊntɚ ",
        "type": "verb",
        "defineEn": "to be faced with an unexpected difficulty during a process",
        "defineVi": "phải đối mặt với một khó khăn bất ngờ trong một quá trình"
    },
    {
        "id": "d1f6c290-0ea5-49d1-94f6-8cded11d18cc",
        "word": "to endanger",
        "phonetic": "tʊ ɛndeɪndʒɚ ",
        "type": "verb",
        "defineEn": "to put someone or something in harm's way",
        "defineVi": "để đặt một ai đó hoặc một cái gì đó theo cách có hại"
    },
    {
        "id": "c2893c4e-445f-47b8-af02-1ef33baf2ee8",
        "word": "to harm",
        "phonetic": "tə hɑːɹm ",
        "type": "verb",
        "defineEn": "to hurt someone or damage something",
        "defineVi": "để làm tổn thương một ai đó hoặc thiệt hại một cái gì đó"
    },
    {
        "id": "a37618ed-1621-40df-8c20-cf4a9c0f686e",
        "word": "to pose",
        "phonetic": "tə poʊz ",
        "type": "verb",
        "defineEn": "to introduce danger, a threat, problem, etc.",
        "defineVi": "để giới thiệu nguy hiểm, một mối đe dọa, vấn đề, vv"
    },
    {
        "id": "14d6e369-b04e-444e-aec6-1d94ed696400",
        "word": "to threaten",
        "phonetic": "tə θɹɛʔn̩ ",
        "type": "verb",
        "defineEn": "to say that one is willing to damage something or hurt someone if one's demands are not met",
        "defineVi": "để nói rằng một người sẵn sàng làm hỏng một cái gì đó hoặc làm tổn thương ai đó nếu nhu cầu của một người không được đáp ứng",
        "hasImg": true
    },
    {
        "id": "ee10379a-dc8a-49c0-947f-554a69ad0d94",
        "word": "happening",
        "phonetic": "hæpənɪŋ ",
        "type": "noun",
        "defineEn": "an event or something that happens",
        "defineVi": "một sự kiện hoặc một cái gì đó xảy ra"
    },
    {
        "id": "7e5d751c-6e55-42f0-90e7-259bfba3559f",
        "word": "to rescue",
        "phonetic": "tə ɹɛskjuː ",
        "type": "verb",
        "defineEn": "to save a person or thing from danger, harm, or a bad situation",
        "defineVi": "để cứu một người hoặc điều từ nguy hiểm, tổn hại, hoặc một tình huống xấu",
        "hasImg": true
    },
    {
        "id": "2e3b52ab-0fd1-441f-9b2c-cf2d4761e5ad",
        "word": "rescuer",
        "phonetic": "ɹɛskjuːɚ ",
        "type": "noun",
        "defineEn": "someone who saves a person or animal from a critical or harmful situation",
        "defineVi": "một người cứu một người hoặc động vật từ một tình huống nghiêm trọng hoặc có hại"
    },
    {
        "id": "e72397fd-1be6-4f62-bf5a-323d97d09bc1",
        "word": "threat",
        "phonetic": "θɹɛt ",
        "type": "noun",
        "defineEn": "someone or something that is possible to cause danger, trouble, or harm",
        "defineVi": "một ai đó hoặc một cái gì đó có thể gây nguy hiểm, rắc rối, hoặc làm hại"
    },
    {
        "id": "169d139a-8366-478d-a383-62e11f2dc0eb",
        "word": "out of harm\\'s way",
        "phonetic": "aʊɾəv hɑːɹm bækslæʃ ɛs weɪ ",
        "type": "phrase",
        "defineEn": "in a place or position that is safe from danger or damage",
        "defineVi": "ở một nơi hoặc vị trí an toàn khỏi nguy hiểm hoặc thiệt hại"
    },
    {
        "id": "428d96e7-a65c-40e7-841b-372bfee033eb",
        "word": "to disturb",
        "phonetic": "tə dɪstɜːb ",
        "type": "verb",
        "defineEn": "to trouble someone and make them uneasy",
        "defineVi": "gây rắc rối cho ai đó và khiến họ khó chịu",
        "hasImg": true
    },
    {
        "id": "6a0dbd18-6e8c-4bba-9218-743ca92b455d",
        "word": "to offend",
        "phonetic": "tʊ əfɛnd ",
        "type": "verb",
        "defineEn": "to cause someone to feel disrespected, upset, etc.",
        "defineVi": "để khiến ai đó cảm thấy không được tôn trọng, khó chịu, v.v."
    },
    {
        "id": "7b8ed49d-318e-4d2d-961d-0ee5512401ec",
        "word": "off the hook",
        "phonetic": "ɔf ðə hʊk ",
        "type": "phrase",
        "defineEn": "no longer facing a difficulty, danger, or punishment",
        "defineVi": "không còn phải đối mặt với một khó khăn, nguy hiểm, hoặc hình phạt"
    },
    {
        "id": "60d51340-18f7-4c01-a8b1-ee9c245fb853",
        "word": "to scream",
        "phonetic": "tə skɹiːm ",
        "type": "verb",
        "defineEn": "to give a long loud shout when we are feeling a strong emotion",
        "defineVi": "để hét to khi chúng ta đang cảm thấy một cảm xúc mạnh mẽ",
        "hasImg": true
    },
    {
        "id": "ee194676-709c-4015-9c85-2fa8d0782010",
        "word": "neutral",
        "phonetic": "nuːtɹəl ",
        "type": "adjective",
        "defineEn": "not taking any sides in a conflict, competition, or dispute and remaining impartial",
        "defineVi": "không đứng về phía nào trong một cuộc xung đột, cạnh tranh hoặc tranh chấp và giữ thái độ vô tư",
        "hasImg": true
    },
    {
        "id": "374ad97e-cea9-4141-9e51-a0ec460b2048",
        "word": "to alert",
        "phonetic": "tʊ ɐlɜːt ",
        "type": "verb",
        "defineEn": "to warn someone of a possible danger",
        "defineVi": "để cảnh báo ai đó về một mối nguy hiểm có thể"
    },
    {
        "id": "fed8c945-af3f-457d-ae18-8c464e77483c",
        "word": "disrespectful",
        "phonetic": "dɪsɹɪspɛktfəl ",
        "type": "adjective",
        "defineEn": "behaving or talking in a way that is offensive to a person or thing",
        "defineVi": "cư xử hoặc nói chuyện theo cách gây khó chịu cho một người hoặc vật",
        "hasImg": true
    },
    {
        "id": "8e1c4dd7-de59-47f5-a00f-69b6373d5c93",
        "word": "on the / a razor\\'s edge",
        "phonetic": "ɔnðə slæʃ ɐ ɹeɪzɚ bækslæʃ ɛs ɛdʒ ",
        "type": "phrase",
        "defineEn": "to be in a very critical state in a way that any mistake can put one in danger",
        "defineVi": "ở trong tình trạng rất quan trọng theo cách mà bất kỳ sai lầm nào cũng có thể khiến một người gặp nguy hiểm"
    },
    {
        "id": "b1e151f0-0a1e-46e6-9454-93a20bf1fa89",
        "word": "fearsome",
        "phonetic": "fɪɹsʌm ",
        "type": "adjective",
        "defineEn": "provoking a feeling of dread",
        "defineVi": "kích động một cảm giác sợ hãi"
    }
]