{
    "id": "d45f43f9-7289-405c-9cc7-f9ed6c3d8d07",
    "title": "Light Brown Shades",
    "originalTitle": "Light Brown Shades",
    "words": [
        {
            "id": "05c761d8-5312-4dc1-8e5d-fbfdacf45f4b",
            "word": "almond",
            "phonetic": "ɔlmənd ",
            "partOfSpeechType": "adjective",
            "examples": [
                "The monkey skillfully plucked the almonds from the tree.",
                "The carob-covered almonds provided a delightful crunch and a hint of sweetness in every bite.",
                "She discovered almond paste as a perfect substitute for cream cheese in her cheesecake recipe.",
                "As a vegan, she substituted almond butter for traditional dairy-based spreads.",
                "For a gluten-free option, substitute regular flour with almond flour in the cake recipe."
            ],
            "audio": "https://tts.langeek.co/read?text=YWxtb25k&hash=f24639651a6bd753a45e54c5a12aa22a7b8db303&lang=en&cache-only=0",
            "defineEn": "a light beige color, resembling the shade of the nut of the same name",
            "defineVi": "màu be nhạt, giống như bóng của loại hạt cùng tên",
            "hasImg": true
        },
        {
            "id": "e33e3915-fa98-4e54-a30f-fdde00180947",
            "word": "beige",
            "phonetic": "beɪʒ ",
            "partOfSpeechType": "adjective",
            "examples": [
                "Well, Bernie shuffled in the night before and went straight to our beige section.",
                "The brand that once challenged consumers to look beyond the beige filed for bankruptcy in February 2010 after years of lackluster sales.",
                "There is somethin' kind of unnerving about the juxtaposition of modern RGB aesthetics and old-school red and beige and tan plastics.",
                "The resulting liquid was a translucent beige that more closely resembled today's ginger ale.",
                "It was a sort of a return to fun in consumer design when things had been kind of beige and rectilinear and straightforward for so long."
            ],
            "audio": "https://tts.langeek.co/read?text=YmVpZ2U&hash=ffdbade4ef42e852fc6e293b02bdc9ecdf241c3a&lang=en&cache-only=0",
            "defineEn": "having a pale brown color like sand",
            "defineVi": "có màu nâu nhạt như cát",
            "hasImg": true
        },
        {
            "id": "f20cbc5f-e4af-4ac1-b027-6d929f085001",
            "word": "khaki",
            "phonetic": "kæki ",
            "partOfSpeechType": "adjective",
            "examples": [
                "He came out with his khaki pants, a sweatshirt and that was it, and not a dime in his pockets."
            ],
            "audio": "https://tts.langeek.co/read?text=a2hha2k&hash=d45f7129786094ee98cb759a630313431df538ed&lang=en&cache-only=0",
            "defineEn": "having a dull yellowish-brown color",
            "defineVi": "có màu nâu vàng xỉn",
            "hasImg": true
        },
        {
            "id": "1d9ec4a6-7f21-4c64-9f61-a64972b87146",
            "word": "tumbleweed",
            "phonetic": "tʌmbəlwiːd ",
            "partOfSpeechType": "adjective",
            "examples": [
                "Tumbleweeds start out as tiny seedlings.",
                "But the tumbleweed takes matters into its own hands.",
                "Tumbleweeds have an unusual way of getting around.",
                "There was tumbleweeds on Flinders Street Station.",
                "Gusts of wind easily break the dead tumbleweed from its roots."
            ],
            "audio": "https://tts.langeek.co/read?text=dHVtYmxld2VlZA&hash=41f153baaeccba853332e27aa87891081c8e092e&lang=en&cache-only=0",
            "defineEn": "a warm and earthy shade of light brown with a hint of yellow or beige",
            "defineVi": "một sắc thái ấm áp và màu đất của màu nâu nhạt với một chút màu vàng hoặc màu be",
            "hasImg": true
        },
        {
            "id": "5a212449-360c-498b-91d4-7423a9b73743",
            "word": "antique brass",
            "phonetic": "æntiːk bɹæs ",
            "partOfSpeechType": "adjective",
            "examples": [],
            "audio": "https://tts.langeek.co/read?text=YW50aXF1ZSBicmFzcw&hash=ad9606fc7c80e36f50f239cf4bc85221e98b29bb&lang=en&cache-only=0",
            "defineEn": "a warm, muted golden-brown color with a slightly aged or patinaed appearance, reminiscent of vintage brass hardware or fixtures",
            "defineVi": "màu nâu vàng trầm, ấm áp với bề ngoài hơi cũ hoặc có lớp gỉ, gợi nhớ đến phần cứng hoặc đồ đạc bằng đồng cổ điển",
            "hasImg": true
        },
        {
            "id": "2ec83654-eff2-41d6-9b1f-7ff148f850b9",
            "word": "cafe au lait",
            "phonetic": "kæfeɪ oʊ leɪt ",
            "partOfSpeechType": "adjective",
            "examples": [
                "Beignets are pillowy fried dough squares, smothered in powdered sugar and eaten hot with: New Orleans’ famous café au lait."
            ],
            "audio": "https://tts.langeek.co/read?text=Y2FmZSBhdSBsYWl0&hash=f5ba6c106c533907352e17ad64d1a9444a1b1fea&lang=en&cache-only=0",
            "defineEn": "a warm, creamy brown color that resembles the color of coffee with milk",
            "defineVi": "màu nâu kem ấm áp giống như màu của cà phê với sữa"
        },
        {
            "id": "a9baf0f8-0ab5-4979-a031-611a7d16c8b6",
            "word": "tan",
            "phonetic": "tæn ",
            "partOfSpeechType": "adjective",
            "examples": [
                "- I like a smooth tan look.",
                "So you can sit here, you can get a tan, for the 41st floor on Billionaires' Row.",
                "So I have to constrict the range on the inverse tan function.",
                "[Both] No! - This is going to be the sickest tan ever.",
                "By the way there are cos and tan buttons on your calculator as well."
            ],
            "audio": "https://tts.langeek.co/read?text=dGFu&hash=6d208e824ab7f0443f7f4661949aa68a5b6941df&lang=en&cache-only=0",
            "defineEn": "pale yellowish-brown",
            "defineVi": "nâu vàng nhạt",
            "hasImg": true
        },
        {
            "id": "2ac30dec-d105-44d1-921f-e2653dcc3d64",
            "word": "ecru",
            "phonetic": "ɛkɹuː ",
            "partOfSpeechType": "adjective",
            "examples": [
                "ecru shimmer wrap, but why be precious about something that’s gonna end up in the garbage?"
            ],
            "audio": "https://tts.langeek.co/read?text=ZWNydQ&hash=11511020c38f572797afe5e4651a14334e0098db&lang=en&cache-only=0",
            "defineEn": "having a light beige color like that of unbleached linen",
            "defineVi": "có màu be nhạt giống như màu của vải lanh chưa tẩy trắng",
            "hasImg": true
        },
        {
            "id": "cf929f2f-54f9-43d9-a3b7-68eaa465eefe",
            "word": "fawn",
            "phonetic": "fɔːn ",
            "partOfSpeechType": "adjective",
            "examples": [
                "Fawns have very sensitive stomachs, and they require very specific food.",
                "Baby deer, or fawns, are born in spring or early summer.",
                "So female deer will usually hide their fawns in tall grass or brush, but they'll sometimes pick more open areas like our backyards.",
                "The fawn will help nourish them and help them survive. ",
                "While fans of other racing series fawn over world-class drivers, in Roborace it's programmers who are the real stars."
            ],
            "audio": "https://tts.langeek.co/read?text=ZmF3bg&hash=5b24018225b516283e408024dbe67ee78eb675f8&lang=en&cache-only=0",
            "defineEn": "a light, pale brownish-tan color, often reminiscent of the coat color of young deer",
            "defineVi": "màu nâu nhạt, nâu nhạt, thường gợi nhớ đến màu lông của hươu non",
            "hasImg": true
        },
        {
            "id": "b6f1088d-1461-4ba1-9b49-efff83efc817",
            "word": "camel",
            "phonetic": "kæməl ",
            "partOfSpeechType": "adjective",
            "examples": [
                "We can't afford to strain at gnats and swallow camels.",
                "It had been a difficult week, so when the car broke down, it was the straw that broke the camel's back.",
                "I just ate camel!",
                "Camel milk is costly.",
                "Camel milk can cost you $30 per liter."
            ],
            "audio": "https://tts.langeek.co/read?text=Y2FtZWw&hash=0069a4e4efaf0721e5b7f7277cbf729b71efe827&lang=en&cache-only=0",
            "defineEn": "a light to medium, warm tan or beige color, resembling the natural color of camel hair",
            "defineVi": "màu nhạt đến trung bình, màu nâu ấm hoặc màu be, giống như màu tự nhiên của lông lạc đà",
            "hasImg": true
        },
        {
            "id": "908220e5-64e0-4ea9-8ea0-78ab4531093f",
            "word": "fallow",
            "phonetic": "fæloʊ ",
            "partOfSpeechType": "adjective",
            "examples": [
                "But, right now, it's fallow season for electioneering.",
                "Instead, its closest living relatives seem to either the red deer or the fallow deer."
            ],
            "audio": "https://tts.langeek.co/read?text=ZmFsbG93&hash=b77aee5020f7cf38f9dce9adf78a11211da5cff6&lang=en&cache-only=0",
            "defineEn": "a pale, light brown color resembling the color of dried leaves or soil",
            "defineVi": "một màu nâu nhạt, nhạt giống như màu của lá khô hoặc đất",
            "hasImg": true
        },
        {
            "id": "4c23f166-9658-41bb-aa18-cba25fa5c63a",
            "word": "earth yellow",
            "phonetic": "ɜːθ jɛloʊ ",
            "partOfSpeechType": "adjective",
            "examples": [],
            "audio": "https://tts.langeek.co/read?text=ZWFydGggeWVsbG93&hash=a9418a3cb2c9c1ad4ba20724db4177b15ef1e6c7&lang=en&cache-only=0",
            "defineEn": "a warm, rich yellow color that resembles the color of natural earth",
            "defineVi": "một màu vàng ấm áp, phong phú giống như màu của trái đất tự nhiên",
            "hasImg": true
        },
        {
            "id": "716dacff-03d6-4e2c-954e-b76bbc8e1781",
            "word": "caramel brown",
            "phonetic": "kæɹəməl bɹaʊn ",
            "partOfSpeechType": "adjective",
            "examples": [],
            "audio": "https://tts.langeek.co/read?text=Y2FyYW1lbCBicm93bg&hash=2fd52134fa396f045fba5ab9df55e1579101606a&lang=en&cache-only=0",
            "defineEn": "having the color of caramel; of a moderate yellow-brown",
            "defineVi": "có màu caramel; có màu vàng nâu vừa phải"
        },
        {
            "id": "874a1cb0-15b1-4bd0-baeb-e5ff48b6ce23",
            "word": "harvest gold",
            "phonetic": "hɑːɹvɪst ɡoʊld ",
            "partOfSpeechType": "adjective",
            "examples": [],
            "audio": "https://tts.langeek.co/read?text=aGFydmVzdCBnb2xk&hash=74a06b9ab7941f11c713385f17e2b87c0b2880c2&lang=en&cache-only=0",
            "defineEn": "a warm, yellowish-gold color reminiscent of ripe, golden wheat or cornfields during harvest season",
            "defineVi": "một màu vàng ấm, vàng gợi nhớ đến những cánh đồng lúa mì hoặc ngô chín vàng trong mùa thu hoạch",
            "hasImg": true
        },
        {
            "id": "2b4a5202-10bd-46f1-ab2c-fc127194f527",
            "word": "ginger",
            "phonetic": "dʒɪndʒɚ ",
            "partOfSpeechType": "adjective",
            "examples": [
                "She carefully lifted the ginger tuber from the soil.",
                "He brewed a cup of ginger tea to soothe his upset stomach.",
                "He marinated the chicken in a mixture of soy sauce, ginger, and sesame oil for a delicious Asian-inspired flavor.",
                "My Asian friend made a refreshing ramen salad with cold noodles, cucumber, and ginger dressing.",
                "She used ginger essential oil to create a relaxing atmosphere in her bedroom."
            ],
            "audio": "https://tts.langeek.co/read?text=Z2luZ2Vy&hash=8baa6db77458a13be638790b83b77a3bf45b1b4a&lang=en&cache-only=0",
            "defineEn": "(of someone's hair or an animal's fur) bright orange-brown in color",
            "defineVi": "(tóc của ai đó hoặc lông của động vật) có màu nâu cam sáng",
            "hasImg": true
        },
        {
            "id": "db4c4892-d35b-4da6-b26c-ced878730ded",
            "word": "timberwolf",
            "phonetic": "tɪmbɚwʊlf ",
            "partOfSpeechType": "adjective",
            "examples": [
                "Boy that Timberwolf was one.",
                "Look what your sales team was saying about Timberwolf."
            ],
            "audio": "https://tts.langeek.co/read?text=dGltYmVyd29sZg&hash=b10b53b6ead86345295fea259f9b3c86454caa78&lang=en&cache-only=0",
            "defineEn": "a cool and muted grayish-brown color that resembles the natural hue of timber or the fur of a gray wolf",
            "defineVi": "một màu nâu xám mát mẻ và im lặng giống như màu tự nhiên của gỗ hoặc lông của một con sói xám",
            "hasImg": true
        },
        {
            "id": "5c8a3aa3-3ab7-44eb-a6f3-847fcd125d48",
            "word": "brown sugar",
            "phonetic": "bɹaʊn ʃʊɡɚ ",
            "partOfSpeechType": "adjective",
            "examples": [],
            "audio": "https://tts.langeek.co/read?text=YnJvd24gc3VnYXI&hash=d7a23361be983ed62a464d7adba7a5ddff55fe6a&lang=en&cache-only=0",
            "defineEn": "a rich, dark brown color resembling the hue of unrefined or partially refined sugar",
            "defineVi": "một màu nâu đậm, phong phú giống như màu của đường chưa tinh chế hoặc tinh chế một phần",
            "hasImg": true
        },
        {
            "id": "ecf64db0-f767-4ffb-8684-49f33e6a7768",
            "word": "cinereous",
            "phonetic": "sɪnɚɹiəs ",
            "partOfSpeechType": "adjective",
            "examples": [],
            "audio": "https://tts.langeek.co/read?text=Y2luZXJlb3Vz&hash=58377d95818460e906f037c56d8ed59423e4d99f&lang=en&cache-only=0",
            "defineEn": "a pale to light gray color with a hint of blue or brown, resembling the ash-gray color of ashes",
            "defineVi": "màu xám nhạt đến xám nhạt với một chút xanh hoặc nâu, giống như màu xám tro của tro",
            "hasImg": true
        },
        {
            "id": "9af0dd19-eadc-4567-9329-c797be0d4654",
            "word": "biscuit brown",
            "phonetic": "bɪskɪt bɹaʊn ",
            "partOfSpeechType": "adjective",
            "examples": [],
            "audio": "https://tts.langeek.co/read?text=YmlzY3VpdCBicm93bg&hash=5c1907f031f22af5e7d665a01f38761510f12856&lang=en&cache-only=0",
            "defineEn": "a warm, light brown color reminiscent of the color of baked biscuits or cookies",
            "defineVi": "màu nâu nhạt, ấm gợi nhớ đến màu của bánh quy nướng hoặc bánh quy"
        },
        {
            "id": "c58e52eb-185b-4e40-a2b6-ffad746dd02e",
            "word": "wood brown",
            "phonetic": "wʊd bɹaʊn ",
            "partOfSpeechType": "adjective",
            "examples": [],
            "audio": "https://tts.langeek.co/read?text=d29vZCBicm93bg&hash=9192d0607f17b0a69cecd43867dc019a5eb63b15&lang=en&cache-only=0",
            "defineEn": "a rich, warm brown color that resembles the natural color of wood",
            "defineVi": "một màu nâu phong phú, ấm áp giống như màu tự nhiên của gỗ"
        },
        {
            "id": "eee6955a-0334-4960-bd46-359fdafc829d",
            "word": "butterscotch",
            "phonetic": "bʌɾɚskɑːtʃ ",
            "partOfSpeechType": "adjective",
            "examples": [
                "He gifted a jar of homemade butterscotch sauce to his neighbor.",
                "He stirred butterscotch chips into his pancake batter, resulting in a stack of fluffy and caramelized pancakes."
            ],
            "audio": "https://tts.langeek.co/read?text=YnV0dGVyc2NvdGNo&hash=703fa5405a9e712f076c43fe6e19637b5a486796&lang=en&cache-only=0",
            "defineEn": "a warm, golden-brown color that resembles the hue of buttery, sweet butterscotch candies",
            "defineVi": "một màu nâu vàng ấm áp giống như màu sắc của kẹo bơ ngọt ngào",
            "hasImg": true
        },
        {
            "id": "1c477286-28a9-4661-9165-821f5ea3b84b",
            "word": "papaya whip",
            "phonetic": "pɐpaɪə wɪp ",
            "partOfSpeechType": "adjective",
            "examples": [],
            "audio": "https://tts.langeek.co/read?text=cGFwYXlhIHdoaXA&hash=ebfad4ca281a297402795c7cb77213dd92b6a83b&lang=en&cache-only=0",
            "defineEn": "a light and warm shade of pale orange or beige, reminiscent of the color of ripe papaya fruit",
            "defineVi": "một sắc thái nhẹ và ấm áp của màu cam nhạt hoặc màu be, gợi nhớ đến màu của quả đu đủ chín",
            "hasImg": true
        },
        {
            "id": "c0eeacb2-f341-4b81-8e4b-3b443f3f726f",
            "word": "tawny",
            "phonetic": "tɔːni ",
            "partOfSpeechType": "adjective",
            "examples": [],
            "audio": "https://tts.langeek.co/read?text=dGF3bnk&hash=44161e0c2de93025f054ec35331ee75106079387&lang=en&cache-only=0",
            "defineEn": "having a light orange-brown color",
            "defineVi": "có màu nâu cam nhạt",
            "hasImg": true
        },
        {
            "id": "d37f9b31-f8e7-429f-b134-2519124f3474",
            "word": "bisque",
            "phonetic": "biːsk ",
            "partOfSpeechType": "adjective",
            "examples": [
                "And for the orzo we will use some bisque with the head of the langoustine.",
                "- You have the sweet from the bisque.",
                "We are doing the - The Bisque, yeah! -",
                "We could sell this, though, (Rhett) we could call it bung bisque."
            ],
            "audio": "https://tts.langeek.co/read?text=YmlzcXVl&hash=93f06e1dab906b6a9f2129fb8c48b6df22d2cf7d&lang=en&cache-only=0",
            "defineEn": "a pale, light pinkish-brown color that resembles the color of cooked or baked bisque pottery",
            "defineVi": "một màu nâu nhạt, hồng nhạt giống như màu của đồ gốm sứ nấu chín hoặc nung",
            "hasImg": true
        },
        {
            "id": "03ed298e-42c2-46f8-b27c-7c63530ef3ca",
            "word": "satin sheen gold",
            "phonetic": "sætɪn ʃiːn ɡoʊld ",
            "partOfSpeechType": "adjective",
            "examples": [],
            "audio": "https://tts.langeek.co/read?text=c2F0aW4gc2hlZW4gZ29sZA&hash=c0ac1704af47b423c2d0a1cd84003849c3a4ac62&lang=en&cache-only=0",
            "defineEn": "a lustrous, glossy, and luxurious shade of gold with a smooth and silky appearance",
            "defineVi": "một màu vàng bóng, bóng và sang trọng với vẻ ngoài mịn màng và mượt mà",
            "hasImg": true
        }
    ]
}